[
  {
    "ContainingType": "personapi_dotnet.Controllers.EstudioController",
    "Method": "GetEstudiosAsync",
    "RelativePath": "api/Estudio",
    "HttpMethod": "GET",
    "IsController": true,
    "Order": 0,
    "Parameters": [],
    "ReturnTypes": [
      {
        "Type": "System.Collections.Generic.IEnumerable\u00601[[personapi_dotnet.Models.Entities.Estudio, personapi-dotnet, Version=1.0.0.0, Culture=neutral, PublicKeyToken=null]]",
        "MediaTypes": [
          "text/plain",
          "application/json",
          "text/json"
        ],
        "StatusCode": 200
      }
    ]
  },
  {
    "ContainingType": "personapi_dotnet.Controllers.EstudioController",
    "Method": "CreateEstudioAsync",
    "RelativePath": "api/Estudio",
    "HttpMethod": "POST",
    "IsController": true,
    "Order": 0,
    "Parameters": [
      {
        "Name": "estudio",
        "Type": "personapi_dotnet.Models.Entities.Estudio",
        "IsRequired": true
      }
    ],
    "ReturnTypes": [
      {
        "Type": "personapi_dotnet.Models.Entities.Estudio",
        "MediaTypes": [
          "text/plain",
          "application/json",
          "text/json"
        ],
        "StatusCode": 200
      }
    ]
  },
  {
    "ContainingType": "personapi_dotnet.Controllers.EstudioController",
    "Method": "GetEstudioAsync",
    "RelativePath": "api/Estudio/{idProf}/{ccPer}",
    "HttpMethod": "GET",
    "IsController": true,
    "Order": 0,
    "Parameters": [
      {
        "Name": "idProf",
        "Type": "System.Int32",
        "IsRequired": true
      },
      {
        "Name": "ccPer",
        "Type": "System.Int64",
        "IsRequired": true
      }
    ],
    "ReturnTypes": [
      {
        "Type": "personapi_dotnet.Models.Entities.Estudio",
        "MediaTypes": [
          "text/plain",
          "application/json",
          "text/json"
        ],
        "StatusCode": 200
      }
    ]
  },
  {
    "ContainingType": "personapi_dotnet.Controllers.EstudioController",
    "Method": "UpdateEstudioAsync",
    "RelativePath": "api/Estudio/{idProf}/{ccPer}",
    "HttpMethod": "PUT",
    "IsController": true,
    "Order": 0,
    "Parameters": [
      {
        "Name": "idProf",
        "Type": "System.Int32",
        "IsRequired": true
      },
      {
        "Name": "ccPer",
        "Type": "System.Int64",
        "IsRequired": true
      },
      {
        "Name": "estudio",
        "Type": "personapi_dotnet.Models.Entities.Estudio",
        "IsRequired": true
      }
    ],
    "ReturnTypes": []
  },
  {
    "ContainingType": "personapi_dotnet.Controllers.EstudioController",
    "Method": "DeleteEstudioAsync",
    "RelativePath": "api/Estudio/{idProf}/{ccPer}",
    "HttpMethod": "DELETE",
    "IsController": true,
    "Order": 0,
    "Parameters": [
      {
        "Name": "idProf",
        "Type": "System.Int32",
        "IsRequired": true
      },
      {
        "Name": "ccPer",
        "Type": "System.Int64",
        "IsRequired": true
      }
    ],
    "ReturnTypes": []
  },
  {
    "ContainingType": "personapi_dotnet.Controllers.PersonaController",
    "Method": "GetPersonasAsync",
    "RelativePath": "api/Persona",
    "HttpMethod": "GET",
    "IsController": true,
    "Order": 0,
    "Parameters": [],
    "ReturnTypes": [
      {
        "Type": "System.Collections.Generic.IEnumerable\u00601[[personapi_dotnet.Models.Entities.Persona, personapi-dotnet, Version=1.0.0.0, Culture=neutral, PublicKeyToken=null]]",
        "MediaTypes": [
          "text/plain",
          "application/json",
          "text/json"
        ],
        "StatusCode": 200
      }
    ]
  },
  {
    "ContainingType": "personapi_dotnet.Controllers.PersonaController",
    "Method": "CreatePersonaAsync",
    "RelativePath": "api/Persona",
    "HttpMethod": "POST",
    "IsController": true,
    "Order": 0,
    "Parameters": [
      {
        "Name": "persona",
        "Type": "personapi_dotnet.Models.Entities.Persona",
        "IsRequired": true
      }
    ],
    "ReturnTypes": [
      {
        "Type": "personapi_dotnet.Models.Entities.Persona",
        "MediaTypes": [
          "text/plain",
          "application/json",
          "text/json"
        ],
        "StatusCode": 200
      }
    ]
  },
  {
    "ContainingType": "personapi_dotnet.Controllers.PersonaController",
    "Method": "GetPersonaByCc",
    "RelativePath": "api/Persona/{cc}",
    "HttpMethod": "GET",
    "IsController": true,
    "Order": 0,
    "Parameters": [
      {
        "Name": "cc",
        "Type": "System.Int64",
        "IsRequired": true
      }
    ],
    "ReturnTypes": [
      {
        "Type": "personapi_dotnet.Models.Entities.Persona",
        "MediaTypes": [
          "text/plain",
          "application/json",
          "text/json"
        ],
        "StatusCode": 200
      }
    ]
  },
  {
    "ContainingType": "personapi_dotnet.Controllers.PersonaController",
    "Method": "UpdatePersona",
    "RelativePath": "api/Persona/{cc}",
    "HttpMethod": "PUT",
    "IsController": true,
    "Order": 0,
    "Parameters": [
      {
        "Name": "cc",
        "Type": "System.Int64",
        "IsRequired": true
      },
      {
        "Name": "persona",
        "Type": "personapi_dotnet.Models.Entities.Persona",
        "IsRequired": true
      }
    ],
    "ReturnTypes": []
  },
  {
    "ContainingType": "personapi_dotnet.Controllers.PersonaController",
    "Method": "DeletePersona",
    "RelativePath": "api/Persona/{cc}",
    "HttpMethod": "DELETE",
    "IsController": true,
    "Order": 0,
    "Parameters": [
      {
        "Name": "cc",
        "Type": "System.Int64",
        "IsRequired": true
      }
    ],
    "ReturnTypes": []
  },
  {
    "ContainingType": "personapi_dotnet.Controllers.ProfesionController",
    "Method": "GetProfesionAsync",
    "RelativePath": "api/Profesion",
    "HttpMethod": "GET",
    "IsController": true,
    "Order": 0,
    "Parameters": [],
    "ReturnTypes": [
      {
        "Type": "System.Collections.Generic.IEnumerable\u00601[[personapi_dotnet.Models.Entities.Profesion, personapi-dotnet, Version=1.0.0.0, Culture=neutral, PublicKeyToken=null]]",
        "MediaTypes": [
          "text/plain",
          "application/json",
          "text/json"
        ],
        "StatusCode": 200
      }
    ]
  },
  {
    "ContainingType": "personapi_dotnet.Controllers.ProfesionController",
    "Method": "CreateProfesionAsync",
    "RelativePath": "api/Profesion",
    "HttpMethod": "POST",
    "IsController": true,
    "Order": 0,
    "Parameters": [
      {
        "Name": "profesion",
        "Type": "personapi_dotnet.Models.Entities.Profesion",
        "IsRequired": true
      }
    ],
    "ReturnTypes": [
      {
        "Type": "personapi_dotnet.Models.Entities.Profesion",
        "MediaTypes": [
          "text/plain",
          "application/json",
          "text/json"
        ],
        "StatusCode": 200
      }
    ]
  },
  {
    "ContainingType": "personapi_dotnet.Controllers.ProfesionController",
    "Method": "GetProfesionByIdAsync",
    "RelativePath": "api/Profesion/{id}",
    "HttpMethod": "GET",
    "IsController": true,
    "Order": 0,
    "Parameters": [
      {
        "Name": "id",
        "Type": "System.Int32",
        "IsRequired": true
      }
    ],
    "ReturnTypes": [
      {
        "Type": "personapi_dotnet.Models.Entities.Profesion",
        "MediaTypes": [
          "text/plain",
          "application/json",
          "text/json"
        ],
        "StatusCode": 200
      }
    ]
  },
  {
    "ContainingType": "personapi_dotnet.Controllers.ProfesionController",
    "Method": "UpdateProfesionAsync",
    "RelativePath": "api/Profesion/{id}",
    "HttpMethod": "PUT",
    "IsController": true,
    "Order": 0,
    "Parameters": [
      {
        "Name": "id",
        "Type": "System.Int32",
        "IsRequired": true
      },
      {
        "Name": "profesion",
        "Type": "personapi_dotnet.Models.Entities.Profesion",
        "IsRequired": true
      }
    ],
    "ReturnTypes": []
  },
  {
    "ContainingType": "personapi_dotnet.Controllers.ProfesionController",
    "Method": "DeleteProfesionAsync",
    "RelativePath": "api/Profesion/{id}",
    "HttpMethod": "DELETE",
    "IsController": true,
    "Order": 0,
    "Parameters": [
      {
        "Name": "id",
        "Type": "System.Int32",
        "IsRequired": true
      }
    ],
    "ReturnTypes": []
  },
  {
    "ContainingType": "personapi_dotnet.Controllers.TelefonoController",
    "Method": "GetTelefonosAsync",
    "RelativePath": "api/Telefono",
    "HttpMethod": "GET",
    "IsController": true,
    "Order": 0,
    "Parameters": [],
    "ReturnTypes": [
      {
        "Type": "System.Collections.Generic.IEnumerable\u00601[[personapi_dotnet.Models.Entities.Telefono, personapi-dotnet, Version=1.0.0.0, Culture=neutral, PublicKeyToken=null]]",
        "MediaTypes": [
          "text/plain",
          "application/json",
          "text/json"
        ],
        "StatusCode": 200
      }
    ]
  },
  {
    "ContainingType": "personapi_dotnet.Controllers.TelefonoController",
    "Method": "CreateTelefonoAsync",
    "RelativePath": "api/Telefono",
    "HttpMethod": "POST",
    "IsController": true,
    "Order": 0,
    "Parameters": [
      {
        "Name": "telefono",
        "Type": "personapi_dotnet.Models.Entities.Telefono",
        "IsRequired": true
      }
    ],
    "ReturnTypes": [
      {
        "Type": "personapi_dotnet.Models.Entities.Telefono",
        "MediaTypes": [
          "text/plain",
          "application/json",
          "text/json"
        ],
        "StatusCode": 200
      }
    ]
  },
  {
    "ContainingType": "personapi_dotnet.Controllers.TelefonoController",
    "Method": "GetTelefonoByNumAsync",
    "RelativePath": "api/Telefono/{num}",
    "HttpMethod": "GET",
    "IsController": true,
    "Order": 0,
    "Parameters": [
      {
        "Name": "num",
        "Type": "System.String",
        "IsRequired": true
      }
    ],
    "ReturnTypes": [
      {
        "Type": "personapi_dotnet.Models.Entities.Telefono",
        "MediaTypes": [
          "text/plain",
          "application/json",
          "text/json"
        ],
        "StatusCode": 200
      }
    ]
  },
  {
    "ContainingType": "personapi_dotnet.Controllers.TelefonoController",
    "Method": "UpdateTelefonoAsync",
    "RelativePath": "api/Telefono/{num}",
    "HttpMethod": "PUT",
    "IsController": true,
    "Order": 0,
    "Parameters": [
      {
        "Name": "num",
        "Type": "System.String",
        "IsRequired": true
      },
      {
        "Name": "telefono",
        "Type": "personapi_dotnet.Models.Entities.Telefono",
        "IsRequired": true
      }
    ],
    "ReturnTypes": []
  },
  {
    "ContainingType": "personapi_dotnet.Controllers.TelefonoController",
    "Method": "DeleteTelefonoAsync",
    "RelativePath": "api/Telefono/{num}",
    "HttpMethod": "DELETE",
    "IsController": true,
    "Order": 0,
    "Parameters": [
      {
        "Name": "num",
        "Type": "System.String",
        "IsRequired": true
      }
    ],
    "ReturnTypes": []
  }
]